cspb_cli/__init__.py
cspb_cli/cspb_cli.py
cspb_cli/run_cspb_cli.py
cspb_cli-1.0.2.dist-info/LICENSE
cspb_cli-1.0.2.dist-info/METADATA
cspb_cli-1.0.2.dist-info/WHEEL
cspb_cli-1.0.2.dist-info/entry_points.txt
cspb_cli-1.0.2.dist-info/top_level.txt
cspb_cli-1.0.2.dist-info/RECORD
