Metadata-Version: 2.1
Name: cspb-cli
Version: 1.0.2
Summary: CSPB Command Line User Interface package
Home-page: https://github.com/jerry-muir/cspb
Author: Gerard L. Muir
Author-email: jerrymuir65@gmail.com
License: MIT
Keywords: cluster system power cspb raspberry pi cli
Platform: UNKNOWN
Classifier: License :: OSI Approved :: MIT License
Classifier: Operating System :: POSIX :: Linux
Requires-Python: >=3.7
Requires-Dist: smbus
Requires-Dist: cmd2
Requires-Dist: cspb
